datasets/JLT.csv
datasets/JLT.json
datasets/LoanStats3a_Step2.csv
datasets/LoanStats3b_Step2.csv
datasets/LoanStats3c_Step2.csv
datasets/LoanStats3d_Step2.csv
datasets/dataset_list.csv
datasets/generic_monthly.json
datasets/generic_multiperiod.json
datasets/nr_test_case.xlsx
datasets/rating_data.csv
datasets/rating_data_raw.csv
datasets/scenario_data.csv
datasets/sp 2017.csv
datasets/sp_1981-2016.csv
datasets/sp_1981-2016.json
datasets/sp_NR_adjusted.json
datasets/sp_multiperiod.json
datasets/synthetic_data.csv
datasets/synthetic_data1.csv
datasets/synthetic_data10.csv
datasets/synthetic_data2.csv
datasets/synthetic_data3.csv
datasets/synthetic_data4.csv
datasets/synthetic_data5.csv
datasets/synthetic_data6.csv
datasets/synthetic_data7.csv
datasets/synthetic_data8.csv
datasets/synthetic_data9.csv
datasets/test.csv
examples/python/README.md
examples/python/__init__.py
examples/python/adjust_nr_state.py
examples/python/characterize_datasets.py
examples/python/compare_estimators.py
examples/python/credit_curves.py
examples/python/data_cleaning_example.py
examples/python/deterministic_paths.py
examples/python/empirical_transition_matrix.py
examples/python/estimate_matrix.py
examples/python/example_list.csv
examples/python/fix_multiperiod_matrix.py
examples/python/generate_full_multiperiod_set.py
examples/python/generate_synthetic_data.py
examples/python/generate_visuals.py
examples/python/matrix_from_cohort_data.py
examples/python/matrix_from_duration_data.py
examples/python/matrix_lendingclub.py
examples/python/matrix_operations.py
examples/python/matrix_set_lendingclub.py
examples/python/matrix_set_operations.py
examples/python/state_space_operations.py
examples/python/__pycache__/__init__.cpython-37.pyc
examples/python/__pycache__/adjust_nr_state.cpython-37.pyc
transitionMatrix/__init__.py
transitionMatrix/model.py
transitionMatrix/creditratings/creditcurve.py
transitionMatrix/creditratings/creditsystems.py
transitionMatrix/creditratings/predefined.py
transitionMatrix-0.5.1.dist-info/LICENSE.txt
transitionMatrix-0.5.1.dist-info/METADATA
transitionMatrix-0.5.1.dist-info/WHEEL
transitionMatrix-0.5.1.dist-info/top_level.txt
transitionMatrix-0.5.1.dist-info/RECORD
