Metadata-Version: 2.1
Name: transitionMatrix
Version: 0.5.1
Summary: A Python powered library for statistical analysis and visualization of state transition phenomena
Home-page: https://github.com/open-risk/transitionMatrix
Author: Open Risk
Author-email: info@openrisk.eu
License: UNKNOWN
Platform: UNKNOWN
Classifier: Intended Audience :: Developers
Classifier: Intended Audience :: Science/Research
Classifier: Intended Audience :: Financial and Insurance Industry
Classifier: Development Status :: 3 - Alpha
Classifier: License :: OSI Approved :: Apache Software License
Classifier: Operating System :: OS Independent
Classifier: Programming Language :: Python :: 3 :: Only
Classifier: Programming Language :: Python :: 3.7
Classifier: Topic :: Scientific/Engineering
Classifier: Topic :: Scientific/Engineering :: Information Analysis
Provides: transitionMatrix
Requires-Dist: pandas
Requires-Dist: numpy
Requires-Dist: scipy
Requires-Dist: statsmodels
Requires-Dist: sympy
Requires-Dist: matplotlib
